LICENSE.txt
MANIFEST.in
README.md
main.py
setup.cfg
setup.py
crafter/__init__.py
crafter/crafter.py
crafter/commands/__init__.py
crafter/commands/create_controller.py
crafter/commands/create_model.py
crafter/commands/create_relationship.py
crafter/commands/create_route.py
crafter/templates/assoc_table.tpl
crafter/templates/controller.tpl
crafter/templates/form.tpl
crafter/templates/model.tpl
crafter/templates/route.tpl
flask_mvc_crafter.egg-info/PKG-INFO
flask_mvc_crafter.egg-info/SOURCES.txt
flask_mvc_crafter.egg-info/dependency_links.txt
flask_mvc_crafter.egg-info/entry_points.txt
flask_mvc_crafter.egg-info/requires.txt
flask_mvc_crafter.egg-info/top_level.txt