Metadata-Version: 2.1
Name: flask-mvc-crafter
Version: 0.1.1
Summary: A CLI tool for the FlaskMVC Starter Kit
Home-page: https://github.com/rdp-jr/crafter
Author: Obee Principio
Author-email: rdprincipio.jr@gmail.com
License: UNKNOWN
Download-URL: https://github.com/rdp-jr/crafter/archive/refs/tags/0.1.1.tar.gz
Platform: UNKNOWN
Classifier: Programming Language :: Python :: 3
Classifier: Programming Language :: Python :: 3.4
Classifier: Programming Language :: Python :: 3.5
Classifier: Programming Language :: Python :: 3.6
License-File: LICENSE.txt
